pyIndego/__init__.py
pyIndego/const.py
pyIndego/helpers.py
pyIndego/indego_async_client.py
pyIndego/indego_base_client.py
pyIndego/indego_client.py
pyIndego/states.py
pyIndego/version.py
tests/__init__.py
tests/test_indego.py
pyIndego-3.2.2.dist-info/LICENSE.txt
pyIndego-3.2.2.dist-info/METADATA
pyIndego-3.2.2.dist-info/WHEEL
pyIndego-3.2.2.dist-info/top_level.txt
pyIndego-3.2.2.dist-info/RECORD
