Metadata-Version: 2.1
Name: pyIndego
Version: 3.2.2
Summary: API for Bosch Indego mower
Home-page: https://github.com/sander1988/pyIndego
Author: jm-73, sander1988
Author-email: jens@myretyr.se
Classifier: Programming Language :: Python :: 3
Classifier: License :: OSI Approved :: MIT License
Classifier: Operating System :: OS Independent
License-File: LICENSE.txt
Requires-Dist: requests
Requires-Dist: aiohttp
Requires-Dist: pytz
Provides-Extra: testing
Requires-Dist: pytest ; extra == 'testing'
Requires-Dist: pytest-asyncio ; extra == 'testing'
Requires-Dist: pytest-cov ; extra == 'testing'
Requires-Dist: mock ; extra == 'testing'
